img_fit/__init__.py
img_fit/__main__.py
imgfit-0.3.2.dist-info/licenses/LICENSE
imgfit-0.3.2.dist-info/METADATA
imgfit-0.3.2.dist-info/WHEEL
imgfit-0.3.2.dist-info/entry_points.txt
imgfit-0.3.2.dist-info/top_level.txt
imgfit-0.3.2.dist-info/RECORD
