Metadata-Version: 2.4
Name: imgfit
Version: 0.3.2
Summary: Change your images.
Home-page: https://github.com/xystudio889/imgfit
Author: xystudio
Author-email: xystudio <173288240@qq.com>
License: MIT License
Keywords: img,pillow,fit,latex
Classifier: Programming Language :: Python :: 3
Classifier: License :: OSI Approved :: MIT License
Classifier: Operating System :: OS Independent
Requires-Python: >=3.7
License-File: LICENSE
Requires-Dist: pillow>=8
Requires-Dist: matplotlib>=3.4
Requires-Dist: PyLaTeXenc>=2
Dynamic: author
Dynamic: home-page
Dynamic: license-file
Dynamic: requires-python
